djtools/__init__.py
djtools/socialnetworks/__init__.py
djtools/socialnetworks/admin.py
djtools/socialnetworks/apps.py
djtools/socialnetworks/context_processors.py
djtools/socialnetworks/forms.py
djtools/socialnetworks/models.py
djtools/socialnetworks/migrations/0001_initial.py
djtools/socialnetworks/migrations/__init__.py
djtools/socialnetworks/templates/djtools/socialnetworks/social_networks.html
django_tools_socialnetworks-1.1.4.dist-info/LICENSE
django_tools_socialnetworks-1.1.4.dist-info/METADATA
django_tools_socialnetworks-1.1.4.dist-info/WHEEL
django_tools_socialnetworks-1.1.4.dist-info/top_level.txt
django_tools_socialnetworks-1.1.4.dist-info/RECORD
